README.rst
setup.py
dcmutils/C_snode.py
dcmutils/C_stringCore.py
dcmutils/__init__.py
dcmutils/_colors.py
dcmutils/dcm_tag.py
dcmutils/debug.py
dcmutils/dgmsocket.py
dcmutils/message.py
dcmutils.egg-info/PKG-INFO
dcmutils.egg-info/SOURCES.txt
dcmutils.egg-info/dependency_links.txt
dcmutils.egg-info/not-zip-safe
dcmutils.egg-info/requires.txt
dcmutils.egg-info/top_level.txt