Metadata-Version: 1.0
Name: dcmutils
Version: 0.99.3
Summary: A collection of DICOM related utilities
Home-page: https://github.com/FNNDSC/pfcon
Author: Rudolph Pienaar
Author-email: rudolph.pienaar@gmail.com
License: MIT
Platform: UNKNOWN
